utils_hj3415/.DS_Store
utils_hj3415/__init__.py
utils_hj3415/logger.py
utils_hj3415/noti.py
utils_hj3415/tools/__init__.py
utils_hj3415/tools/date.py
utils_hj3415/tools/helpers.py
utils_hj3415/tools/numbers.py
utils_hj3415/tools/pc.py
utils_hj3415-3.2.6.dist-info/WHEEL
utils_hj3415-3.2.6.dist-info/METADATA
utils_hj3415-3.2.6.dist-info/RECORD
