Metadata-Version: 2.3
Name: utils_hj3415
Version: 3.2.6
Summary: The collection of utility functions for hj3415
Author-email: Hyungjin Kim <hj3415@gmail.com>
Classifier: License :: OSI Approved :: MIT License
Requires-Dist: python-telegram-bot>=21.9
Requires-Dist: nest-asyncio>=1.6.0
Requires-Dist: pydantic
Requires-Dist: pymongo
Project-URL: Home, https://www.hyungjin.kr
